{
  "bookGuiScale": 0,
  "clickedVisualize": false,
  "bookData": {
    "touhou_little_maid:memorizable_gensokyo": {
      "viewedEntries": [
        "touhou_little_maid:overview/what_is_touhou",
        "touhou_little_maid:overview/power_point",
        "touhou_little_maid:overview/world_spawn",
        "touhou_little_maid:maid/spawn_maid",
        "touhou_little_maid:maid/maid_task"
      ],
      "bookmarks": [],
      "history": [
        "touhou_little_maid:maid/maid_task",
        "touhou_little_maid:maid/spawn_maid",
        "touhou_little_maid:overview/world_spawn",
        "touhou_little_maid:overview/power_point",
        "touhou_little_maid:overview/what_is_touhou"
      ],
      "completedManualQuests": []
    }
  }
}